{
  "config": "{\"version\":\"5.59\",\"themeCollection\":{\"baseTheme\":{\"name\":\"CY24SU10\",\"type\":2,\"version\":\"5.59\"}},\"activeSectionIndex\":0,\"defaultDrillFilterOtherVisuals\":true,\"linguisticSchemaSyncVersion\":2,\"settings\":{\"useNewFilterPaneExperience\":true,\"allowChangeFilterTypes\":true,\"useStylableVisualContainerHeader\":true,\"queryLimitOption\":6,\"exportDataMode\":1,\"useDefaultAggregateDisplayName\":true,\"useEnhancedTooltips\":true,\"filterPaneHiddenInEditMode\":false},\"objects\":{\"section\":[{\"properties\":{\"verticalAlignment\":{\"expr\":{\"Literal\":{\"Value\":\"'Top'\"}}}}}],\"outspacePane\":[{\"properties\":{\"expanded\":{\"expr\":{\"Literal\":{\"Value\":\"false\"}}}}}]}}",
  "layoutOptimization": 0,
  "resourcePackages": [
    {
      "resourcePackage": {
        "disabled": false,
        "items": [
          {
            "name": "CY24SU10",
            "path": "BaseThemes/CY24SU10.json",
            "type": 202
          }
        ],
        "name": "SharedResources",
        "type": 2
      }
    }
  ],
  "sections": [
    {
      "config": "{\"objects\":{\"background\":[{\"properties\":{\"color\":{\"solid\":{\"color\":{\"expr\":{\"ThemeDataColor\":{\"ColorId\":0,\"Percent\":0}}}}}}}],\"pageRefresh\":[{\"properties\":{\"show\":{\"expr\":{\"Literal\":{\"Value\":\"false\"}}}}}],\"outspace\":[{\"properties\":{\"color\":{\"solid\":{\"color\":{\"expr\":{\"Literal\":{\"Value\":\"'#F8EEEE'\"}}}}}}}]},\"type\":1}",
      "displayName": "Strona 1",
      "displayOption": 1,
      "filters": "[]",
      "height": 936.00,
      "name": "9545aafc44952e3f4d61",
      "visualContainers": [
        {
          "config": "{\"name\":\"0a3b4d7862c961db5e2c\",\"layouts\":[{\"id\":0,\"position\":{\"x\":617.3865336658355,\"y\":510.01496259351626,\"z\":5000,\"width\":429.48628428927685,\"height\":380.4688279301746,\"tabOrder\":2000}}],\"singleVisual\":{\"visualType\":\"columnChart\",\"projections\":{\"Category\":[{\"queryRef\":\"analytics top_fuel_revenue.fuel_type\",\"active\":true}],\"Y\":[{\"queryRef\":\"Sum(analytics top_fuel_revenue.total_cost)\"}]},\"prototypeQuery\":{\"Version\":2,\"From\":[{\"Name\":\"a\",\"Entity\":\"analytics top_fuel_revenue\",\"Type\":0}],\"Select\":[{\"Column\":{\"Expression\":{\"SourceRef\":{\"Source\":\"a\"}},\"Property\":\"fuel_type\"},\"Name\":\"analytics top_fuel_revenue.fuel_type\",\"NativeReferenceName\":\"fuel_type\"},{\"Aggregation\":{\"Expression\":{\"Column\":{\"Expression\":{\"SourceRef\":{\"Source\":\"a\"}},\"Property\":\"total_cost\"}},\"Function\":0},\"Name\":\"Sum(analytics top_fuel_revenue.total_cost)\",\"NativeReferenceName\":\"Suma element贸w total_cost\"}],\"OrderBy\":[{\"Direction\":2,\"Expression\":{\"Aggregation\":{\"Expression\":{\"Column\":{\"Expression\":{\"SourceRef\":{\"Source\":\"a\"}},\"Property\":\"total_cost\"}},\"Function\":0}}}]},\"drillFilterOtherVisuals\":true,\"hasDefaultSort\":true,\"objects\":{\"categoryAxis\":[{\"properties\":{\"showAxisTitle\":{\"expr\":{\"Literal\":{\"Value\":\"false\"}}}}}],\"valueAxis\":[{\"properties\":{\"showAxisTitle\":{\"expr\":{\"Literal\":{\"Value\":\"false\"}}},\"gridlineShow\":{\"expr\":{\"Literal\":{\"Value\":\"false\"}}}}}],\"labels\":[{\"properties\":{\"show\":{\"expr\":{\"Literal\":{\"Value\":\"true\"}}}}}],\"ribbonBands\":[{\"properties\":{\"show\":{\"expr\":{\"Literal\":{\"Value\":\"false\"}}}}}],\"dataPoint\":[{\"properties\":{\"fill\":{\"solid\":{\"color\":{\"expr\":{\"FillRule\":{\"Input\":{\"Aggregation\":{\"Expression\":{\"Column\":{\"Expression\":{\"SourceRef\":{\"Entity\":\"analytics top_fuel_revenue\"}},\"Property\":\"total_cost\"}},\"Function\":0}},\"FillRule\":{\"linearGradient2\":{\"min\":{\"color\":{\"Literal\":{\"Value\":\"'#e68f96'\"}}},\"max\":{\"color\":{\"Literal\":{\"Value\":\"'#a1343c'\"}}},\"nullColoringStrategy\":{\"strategy\":{\"Literal\":{\"Value\":\"'asZero'\"}}}}}}}}}}},\"selector\":{\"data\":[{\"dataViewWildcard\":{\"matchingOption\":1}}]}}],\"legend\":[{\"properties\":{\"showGradientLegend\":{\"expr\":{\"Literal\":{\"Value\":\"false\"}}},\"show\":{\"expr\":{\"Literal\":{\"Value\":\"false\"}}}}}]},\"vcObjects\":{\"title\":[{\"properties\":{\"text\":{\"expr\":{\"Literal\":{\"Value\":\"'MONTHLY REVENUE BY FUEL TYPE'\"}}},\"alignment\":{\"expr\":{\"Literal\":{\"Value\":\"'center'\"}}}}}]}}}",
          "filters": "[]",
          "height": 380.47,
          "width": 429.49,
          "x": 617.39,
          "y": 510.01,
          "z": 5000.00
        },
        {
          "config": "{\"name\":\"21d483715581621e7e18\",\"layouts\":[{\"id\":0,\"position\":{\"x\":103.87032418952619,\"y\":248.58852867830424,\"z\":11000,\"width\":205.4064837905237,\"height\":150.55361596009976,\"tabOrder\":11000}}],\"singleVisual\":{\"visualType\":\"slicer\",\"projections\":{\"Values\":[{\"queryRef\":\"analytics rolling_orders_sum.dist_date\",\"active\":true}]},\"prototypeQuery\":{\"Version\":2,\"From\":[{\"Name\":\"a\",\"Entity\":\"analytics rolling_orders_sum\",\"Type\":0}],\"Select\":[{\"Column\":{\"Expression\":{\"SourceRef\":{\"Source\":\"a\"}},\"Property\":\"dist_date\"},\"Name\":\"analytics rolling_orders_sum.dist_date\",\"NativeReferenceName\":\"DATE FILTER\"}],\"OrderBy\":[{\"Direction\":1,\"Expression\":{\"Column\":{\"Expression\":{\"SourceRef\":{\"Source\":\"a\"}},\"Property\":\"dist_date\"}}}]},\"columnProperties\":{\"analytics rolling_orders_sum.dist_date\":{\"displayName\":\"DATE FILTER\"}},\"drillFilterOtherVisuals\":true,\"hasDefaultSort\":true,\"objects\":{\"data\":[{\"properties\":{\"mode\":{\"expr\":{\"Literal\":{\"Value\":\"'Between'\"}}}}}],\"general\":[{\"properties\":{\"orientation\":{\"expr\":{\"Literal\":{\"Value\":\"1D\"}}}}}],\"slider\":[{\"properties\":{\"show\":{\"expr\":{\"Literal\":{\"Value\":\"true\"}}}}}]}}}",
          "filters": "[]",
          "height": 150.55,
          "width": 205.41,
          "x": 103.87,
          "y": 248.59,
          "z": 11000.00
        },
        {
          "config": "{\"name\":\"5ef23d165f456d74eaf4\",\"layouts\":[{\"id\":0,\"position\":{\"x\":362.9625935162095,\"y\":66.52369077306733,\"z\":8000,\"width\":1221.9351620947632,\"height\":332.6184538653367,\"tabOrder\":7000}}],\"singleVisual\":{\"visualType\":\"lineChart\",\"projections\":{\"Category\":[{\"queryRef\":\"analytics rolling_orders_sum.full_name\",\"active\":true},{\"queryRef\":\"analytics rolling_orders_sum.dist_date\",\"active\":true}],\"Y\":[{\"queryRef\":\"Sum(analytics rolling_orders_sum.rolling_sum_over_orders)\"}]},\"prototypeQuery\":{\"Version\":2,\"From\":[{\"Name\":\"a\",\"Entity\":\"analytics rolling_orders_sum\",\"Type\":0}],\"Select\":[{\"Aggregation\":{\"Expression\":{\"Column\":{\"Expression\":{\"SourceRef\":{\"Source\":\"a\"}},\"Property\":\"rolling_sum_over_orders\"}},\"Function\":0},\"Name\":\"Sum(analytics rolling_orders_sum.rolling_sum_over_orders)\",\"NativeReferenceName\":\"Suma element贸w rolling_sum_over_orders\"},{\"Column\":{\"Expression\":{\"SourceRef\":{\"Source\":\"a\"}},\"Property\":\"full_name\"},\"Name\":\"analytics rolling_orders_sum.full_name\",\"NativeReferenceName\":\"full_name\"},{\"Column\":{\"Expression\":{\"SourceRef\":{\"Source\":\"a\"}},\"Property\":\"dist_date\"},\"Name\":\"analytics rolling_orders_sum.dist_date\",\"NativeReferenceName\":\"dist_date\"}],\"OrderBy\":[{\"Direction\":1,\"Expression\":{\"Column\":{\"Expression\":{\"SourceRef\":{\"Source\":\"a\"}},\"Property\":\"full_name\"}}},{\"Direction\":1,\"Expression\":{\"Column\":{\"Expression\":{\"SourceRef\":{\"Source\":\"a\"}},\"Property\":\"dist_date\"}}}]},\"drillFilterOtherVisuals\":true,\"hasDefaultSort\":true,\"objects\":{\"categoryAxis\":[{\"properties\":{\"showAxisTitle\":{\"expr\":{\"Literal\":{\"Value\":\"false\"}}}}}],\"valueAxis\":[{\"properties\":{\"showAxisTitle\":{\"expr\":{\"Literal\":{\"Value\":\"false\"}}},\"gridlineColor\":{\"solid\":{\"color\":{\"expr\":{\"ThemeDataColor\":{\"ColorId\":3,\"Percent\":0.2}}}}},\"gridlineShow\":{\"expr\":{\"Literal\":{\"Value\":\"false\"}}}}}],\"labels\":[{\"properties\":{\"show\":{\"expr\":{\"Literal\":{\"Value\":\"true\"}}}}}],\"lineStyles\":[{\"properties\":{\"areaShow\":{\"expr\":{\"Literal\":{\"Value\":\"true\"}}},\"showMarker\":{\"expr\":{\"Literal\":{\"Value\":\"false\"}}},\"lineStyle\":{\"expr\":{\"Literal\":{\"Value\":\"'solid'\"}}}}}],\"dataPoint\":[{\"properties\":{\"fill\":{\"solid\":{\"color\":{\"expr\":{\"ThemeDataColor\":{\"ColorId\":9,\"Percent\":0.4}}}}}},\"selector\":{\"metadata\":\"Sum(analytics rolling_orders_sum.rolling_sum_over_orders)\"}}],\"general\":[{\"properties\":{}}]},\"vcObjects\":{\"title\":[{\"properties\":{\"text\":{\"expr\":{\"Literal\":{\"Value\":\"'SUM OF ORDERS REVENUE PER CUSTOMER'\"}}},\"alignment\":{\"expr\":{\"Literal\":{\"Value\":\"'center'\"}}}}}],\"visualHeader\":[{\"properties\":{\"background\":{\"solid\":{\"color\":{\"expr\":{\"ThemeDataColor\":{\"ColorId\":0,\"Percent\":0}}}}}}}],\"background\":[{\"properties\":{\"color\":{\"solid\":{\"color\":{\"expr\":{\"ThemeDataColor\":{\"ColorId\":0,\"Percent\":0}}}}}}}]}}}",
          "filters": "[]",
          "height": 332.62,
          "width": 1221.94,
          "x": 362.96,
          "y": 66.52,
          "z": 8000.00
        },
        {
          "config": "{\"name\":\"6114b7f19701ed40ddd5\",\"layouts\":[{\"id\":0,\"position\":{\"x\":60.68827930174564,\"y\":156.38902743142145,\"z\":9000,\"width\":287.1022443890274,\"height\":267.2618453865337,\"tabOrder\":9000}}],\"singleVisual\":{\"visualType\":\"shape\",\"drillFilterOtherVisuals\":true,\"objects\":{\"shape\":[{\"properties\":{\"tileShape\":{\"expr\":{\"Literal\":{\"Value\":\"'rectangle'\"}}},\"roundEdge\":{\"expr\":{\"Literal\":{\"Value\":\"10L\"}}}}}],\"rotation\":[{\"properties\":{\"shapeAngle\":{\"expr\":{\"Literal\":{\"Value\":\"0L\"}}}}}],\"fill\":[{\"properties\":{\"fillColor\":{\"solid\":{\"color\":{\"expr\":{\"ThemeDataColor\":{\"ColorId\":0,\"Percent\":0}}}}}},\"selector\":{\"id\":\"default\"}}],\"outline\":[{\"properties\":{\"show\":{\"expr\":{\"Literal\":{\"Value\":\"false\"}}}}}],\"shadow\":[{\"properties\":{\"show\":{\"expr\":{\"Literal\":{\"Value\":\"true\"}}}}},{\"properties\":{\"shadowPositionPreset\":{\"expr\":{\"Literal\":{\"Value\":\"'custom'\"}}},\"transparency\":{\"expr\":{\"Literal\":{\"Value\":\"90D\"}}},\"color\":{\"solid\":{\"color\":{\"expr\":{\"ThemeDataColor\":{\"ColorId\":0,\"Percent\":-0.6}}}}}},\"selector\":{\"id\":\"default\"}}]}},\"howCreated\":\"InsertVisualButton\"}",
          "filters": "[]",
          "height": 267.26,
          "width": 287.10,
          "x": 60.69,
          "y": 156.39,
          "z": 9000.00
        },
        {
          "config": "{\"name\":\"6917f652b94cc18588f1\",\"layouts\":[{\"id\":0,\"position\":{\"x\":80.5286783042394,\"y\":510.01496259351626,\"z\":1000,\"width\":429.48628428927685,\"height\":380.4688279301746,\"tabOrder\":0}}],\"singleVisual\":{\"visualType\":\"columnChart\",\"projections\":{\"Category\":[{\"queryRef\":\"analytics top_weeks_orders.week_period\",\"active\":true}],\"Y\":[{\"queryRef\":\"Sum(analytics top_weeks_orders.weekly_orders)\"}]},\"prototypeQuery\":{\"Version\":2,\"From\":[{\"Name\":\"a\",\"Entity\":\"analytics top_weeks_orders\",\"Type\":0}],\"Select\":[{\"Column\":{\"Expression\":{\"SourceRef\":{\"Source\":\"a\"}},\"Property\":\"week_period\"},\"Name\":\"analytics top_weeks_orders.week_period\",\"NativeReferenceName\":\"Liczba element贸w week_period\"},{\"Aggregation\":{\"Expression\":{\"Column\":{\"Expression\":{\"SourceRef\":{\"Source\":\"a\"}},\"Property\":\"weekly_orders\"}},\"Function\":0},\"Name\":\"Sum(analytics top_weeks_orders.weekly_orders)\",\"NativeReferenceName\":\"weekly_orders\"}],\"OrderBy\":[{\"Direction\":2,\"Expression\":{\"Aggregation\":{\"Expression\":{\"Column\":{\"Expression\":{\"SourceRef\":{\"Source\":\"a\"}},\"Property\":\"weekly_orders\"}},\"Function\":0}}}]},\"drillFilterOtherVisuals\":true,\"hasDefaultSort\":true,\"objects\":{\"categoryAxis\":[{\"properties\":{\"concatenateLabels\":{\"expr\":{\"Literal\":{\"Value\":\"false\"}}},\"showAxisTitle\":{\"expr\":{\"Literal\":{\"Value\":\"false\"}}}}}],\"valueAxis\":[{\"properties\":{\"showAxisTitle\":{\"expr\":{\"Literal\":{\"Value\":\"false\"}}},\"gridlineTransparency\":{\"expr\":{\"Literal\":{\"Value\":\"0D\"}}},\"gridlineAutoScale\":{\"expr\":{\"Literal\":{\"Value\":\"false\"}}},\"gridlineThickness\":{\"expr\":{\"Literal\":{\"Value\":\"1D\"}}},\"gridlineColor\":{\"solid\":{\"color\":{\"expr\":{\"FillRule\":{\"Input\":{\"Aggregation\":{\"Expression\":{\"Column\":{\"Expression\":{\"SourceRef\":{\"Entity\":\"analytics top_weeks_orders\"}},\"Property\":\"week_period\"}},\"Function\":5}},\"FillRule\":{\"linearGradient2\":{\"min\":{\"color\":{\"Literal\":{\"Value\":\"'#f5c4af'\"}},\"value\":{\"Literal\":{\"Value\":\"1D\"}}},\"max\":{\"color\":{\"Literal\":{\"Value\":\"'#ad5129'\"}},\"value\":{\"Literal\":{\"Value\":\"8D\"}}},\"nullColoringStrategy\":{\"strategy\":{\"Literal\":{\"Value\":\"'asZero'\"}}}}}}}}}},\"gridlineShow\":{\"expr\":{\"Literal\":{\"Value\":\"false\"}}}}}],\"ribbonBands\":[{\"properties\":{\"show\":{\"expr\":{\"Literal\":{\"Value\":\"false\"}}}}}],\"labels\":[{\"properties\":{\"show\":{\"expr\":{\"Literal\":{\"Value\":\"true\"}}}}}],\"dataPoint\":[{\"properties\":{\"fill\":{\"solid\":{\"color\":{\"expr\":{\"FillRule\":{\"Input\":{\"Aggregation\":{\"Expression\":{\"Column\":{\"Expression\":{\"SourceRef\":{\"Entity\":\"analytics top_weeks_orders\"}},\"Property\":\"weekly_orders\"}},\"Function\":0}},\"FillRule\":{\"linearGradient2\":{\"min\":{\"color\":{\"Literal\":{\"Value\":\"'#e68f96'\"}}},\"max\":{\"color\":{\"Literal\":{\"Value\":\"'#a1343c'\"}}},\"nullColoringStrategy\":{\"strategy\":{\"Literal\":{\"Value\":\"'asZero'\"}}}}}}}}}}},\"selector\":{\"data\":[{\"dataViewWildcard\":{\"matchingOption\":1}}]}}],\"legend\":[{\"properties\":{\"showGradientLegend\":{\"expr\":{\"Literal\":{\"Value\":\"false\"}}},\"show\":{\"expr\":{\"Literal\":{\"Value\":\"false\"}}}}}]},\"vcObjects\":{\"title\":[{\"properties\":{\"text\":{\"expr\":{\"Literal\":{\"Value\":\"'ORDERS PER WEEK'\"}}},\"alignment\":{\"expr\":{\"Literal\":{\"Value\":\"'center'\"}}},\"titleWrap\":{\"expr\":{\"Literal\":{\"Value\":\"true\"}}}}}]}}}",
          "filters": "[{\"name\":\"0a7e002cd8ac7bb2dd21\",\"expression\":{\"Column\":{\"Expression\":{\"SourceRef\":{\"Entity\":\"analytics top_weeks_orders\"}},\"Property\":\"week_period\"}},\"type\":\"Categorical\",\"howCreated\":0,\"objects\":{\"general\":[{\"properties\":{\"isInvertedSelectionMode\":{\"expr\":{\"Literal\":{\"Value\":\"true\"}}}}}]},\"isHiddenInViewMode\":false}]",
          "height": 380.47,
          "width": 429.49,
          "x": 80.53,
          "y": 510.01,
          "z": 1000.00
        },
        {
          "config": "{\"name\":\"736010ccc6aa283f2e2d\",\"layouts\":[{\"id\":0,\"position\":{\"x\":60.68827930174564,\"y\":25.675810473815464,\"z\":6000,\"width\":287.1022443890274,\"height\":130.713216957606,\"tabOrder\":6000}}],\"singleVisual\":{\"visualType\":\"textbox\",\"drillFilterOtherVisuals\":true,\"objects\":{\"general\":[{\"properties\":{\"paragraphs\":[{\"textRuns\":[{\"value\":\" STATION REPORT\",\"textStyle\":{\"fontWeight\":\"bold\",\"fontSize\":\"32pt\"}}],\"horizontalTextAlignment\":\"center\"}]}}]},\"vcObjects\":{\"background\":[{\"properties\":{\"show\":{\"expr\":{\"Literal\":{\"Value\":\"false\"}}}}}]}}}",
          "filters": "[]",
          "height": 130.71,
          "width": 287.10,
          "x": 60.69,
          "y": 25.68,
          "z": 6000.00
        },
        {
          "config": "{\"name\":\"86063dc4e17415b3b700\",\"layouts\":[{\"id\":0,\"position\":{\"x\":1132.069825436409,\"y\":490,\"z\":2000,\"width\":468,\"height\":420.14962593516213,\"tabOrder\":5000}}],\"singleVisual\":{\"visualType\":\"shape\",\"drillFilterOtherVisuals\":true,\"objects\":{\"shape\":[{\"properties\":{\"tileShape\":{\"expr\":{\"Literal\":{\"Value\":\"'rectangle'\"}}},\"roundEdge\":{\"expr\":{\"Literal\":{\"Value\":\"10L\"}}}}}],\"rotation\":[{\"properties\":{\"shapeAngle\":{\"expr\":{\"Literal\":{\"Value\":\"0L\"}}}}}],\"fill\":[{\"properties\":{\"fillColor\":{\"solid\":{\"color\":{\"expr\":{\"ThemeDataColor\":{\"ColorId\":0,\"Percent\":0}}}}}},\"selector\":{\"id\":\"default\"}}],\"outline\":[{\"properties\":{\"show\":{\"expr\":{\"Literal\":{\"Value\":\"false\"}}}}}],\"shadow\":[{\"properties\":{\"show\":{\"expr\":{\"Literal\":{\"Value\":\"true\"}}}}},{\"properties\":{\"color\":{\"solid\":{\"color\":{\"expr\":{\"ThemeDataColor\":{\"ColorId\":0,\"Percent\":-0.6}}}}},\"transparency\":{\"expr\":{\"Literal\":{\"Value\":\"90D\"}}},\"shadowPositionPreset\":{\"expr\":{\"Literal\":{\"Value\":\"'custom'\"}}}},\"selector\":{\"id\":\"default\"}}]}},\"howCreated\":\"InsertVisualButton\"}",
          "filters": "[]",
          "height": 420.15,
          "width": 468.00,
          "x": 1132.07,
          "y": 490.00,
          "z": 2000.00
        },
        {
          "config": "{\"name\":\"8b3e34480700e21c206f\",\"layouts\":[{\"id\":0,\"position\":{\"x\":103.87032418952619,\"y\":180.89775561097258,\"z\":10000,\"width\":205.4064837905237,\"height\":67.69077306733168,\"tabOrder\":10000}}],\"singleVisual\":{\"visualType\":\"slicer\",\"projections\":{\"Values\":[{\"queryRef\":\"analytics rolling_orders_sum.full_name\",\"active\":true}]},\"prototypeQuery\":{\"Version\":2,\"From\":[{\"Name\":\"a\",\"Entity\":\"analytics rolling_orders_sum\",\"Type\":0}],\"Select\":[{\"Column\":{\"Expression\":{\"SourceRef\":{\"Source\":\"a\"}},\"Property\":\"full_name\"},\"Name\":\"analytics rolling_orders_sum.full_name\",\"NativeReferenceName\":\"FULL NAME FILTER\"}],\"OrderBy\":[{\"Direction\":1,\"Expression\":{\"Column\":{\"Expression\":{\"SourceRef\":{\"Source\":\"a\"}},\"Property\":\"full_name\"}}}]},\"expansionStates\":[{\"roles\":[\"Values\"],\"levels\":[{\"queryRefs\":[\"analytics rolling_orders_sum.full_name\"],\"isCollapsed\":true,\"identityKeys\":[{\"Column\":{\"Expression\":{\"SourceRef\":{\"Entity\":\"analytics rolling_orders_sum\"}},\"Property\":\"full_name\"}}],\"isPinned\":true}],\"root\":{\"identityValues\":null}}],\"columnProperties\":{\"analytics rolling_orders_sum.full_name\":{\"displayName\":\"FULL NAME FILTER\",\"formatString\":\"G\"}},\"drillFilterOtherVisuals\":true,\"hasDefaultSort\":true,\"objects\":{\"data\":[{\"properties\":{\"mode\":{\"expr\":{\"Literal\":{\"Value\":\"'Dropdown'\"}}}}}],\"general\":[{\"properties\":{}}],\"selection\":[{\"properties\":{\"selectAllCheckboxEnabled\":{\"expr\":{\"Literal\":{\"Value\":\"false\"}}},\"strictSingleSelect\":{\"expr\":{\"Literal\":{\"Value\":\"false\"}}},\"singleSelect\":{\"expr\":{\"Literal\":{\"Value\":\"true\"}}}}}]}}}",
          "filters": "[]",
          "height": 67.69,
          "width": 205.41,
          "x": 103.87,
          "y": 180.90,
          "z": 10000.00
        },
        {
          "config": "{\"name\":\"9d8f1687dde691b64b55\",\"layouts\":[{\"id\":0,\"position\":{\"x\":1151.9102244389028,\"y\":510.01496259351626,\"z\":3000,\"width\":429.48628428927685,\"height\":380.4688279301746,\"tabOrder\":1000}}],\"singleVisual\":{\"visualType\":\"columnChart\",\"projections\":{\"Category\":[{\"queryRef\":\"analytics top_weeks_revenue.week_period\",\"active\":true}],\"Y\":[{\"queryRef\":\"Sum(analytics top_weeks_revenue.weekly_revenue)\"}]},\"prototypeQuery\":{\"Version\":2,\"From\":[{\"Name\":\"a\",\"Entity\":\"analytics top_weeks_revenue\",\"Type\":0}],\"Select\":[{\"Column\":{\"Expression\":{\"SourceRef\":{\"Source\":\"a\"}},\"Property\":\"week_period\"},\"Name\":\"analytics top_weeks_revenue.week_period\",\"NativeReferenceName\":\"week_period\"},{\"Aggregation\":{\"Expression\":{\"Column\":{\"Expression\":{\"SourceRef\":{\"Source\":\"a\"}},\"Property\":\"weekly_revenue\"}},\"Function\":0},\"Name\":\"Sum(analytics top_weeks_revenue.weekly_revenue)\",\"NativeReferenceName\":\"Suma element贸w weekly_revenue\"}],\"OrderBy\":[{\"Direction\":2,\"Expression\":{\"Aggregation\":{\"Expression\":{\"Column\":{\"Expression\":{\"SourceRef\":{\"Source\":\"a\"}},\"Property\":\"weekly_revenue\"}},\"Function\":0}}}]},\"drillFilterOtherVisuals\":true,\"hasDefaultSort\":true,\"objects\":{\"labels\":[{\"properties\":{\"show\":{\"expr\":{\"Literal\":{\"Value\":\"true\"}}}}}],\"valueAxis\":[{\"properties\":{\"showAxisTitle\":{\"expr\":{\"Literal\":{\"Value\":\"false\"}}},\"show\":{\"expr\":{\"Literal\":{\"Value\":\"true\"}}},\"gridlineShow\":{\"expr\":{\"Literal\":{\"Value\":\"false\"}}}}}],\"categoryAxis\":[{\"properties\":{\"showAxisTitle\":{\"expr\":{\"Literal\":{\"Value\":\"false\"}}}}}],\"dataPoint\":[{\"properties\":{\"fill\":{\"solid\":{\"color\":{\"expr\":{\"FillRule\":{\"Input\":{\"Aggregation\":{\"Expression\":{\"Column\":{\"Expression\":{\"SourceRef\":{\"Entity\":\"analytics top_weeks_revenue\"}},\"Property\":\"weekly_revenue\"}},\"Function\":0}},\"FillRule\":{\"linearGradient2\":{\"min\":{\"color\":{\"Literal\":{\"Value\":\"'#e68f96'\"}}},\"max\":{\"color\":{\"Literal\":{\"Value\":\"'#a1343c'\"}}},\"nullColoringStrategy\":{\"strategy\":{\"Literal\":{\"Value\":\"'noColor'\"}}}}}}}}}}},\"selector\":{\"data\":[{\"dataViewWildcard\":{\"matchingOption\":1}}]}}],\"legend\":[{\"properties\":{\"showGradientLegend\":{\"expr\":{\"Literal\":{\"Value\":\"false\"}}},\"show\":{\"expr\":{\"Literal\":{\"Value\":\"false\"}}}}}]},\"vcObjects\":{\"title\":[{\"properties\":{\"text\":{\"expr\":{\"Literal\":{\"Value\":\"'WEEKLY REVENUE'\"}}},\"alignment\":{\"expr\":{\"Literal\":{\"Value\":\"'center'\"}}}}}]}}}",
          "filters": "[{\"name\":\"8ef93f9445956672d5e0\",\"expression\":{\"Column\":{\"Expression\":{\"SourceRef\":{\"Entity\":\"analytics top_weeks_revenue\"}},\"Property\":\"week_period\"}},\"type\":\"Categorical\",\"howCreated\":0,\"objects\":{\"general\":[{\"properties\":{\"isInvertedSelectionMode\":{\"expr\":{\"Literal\":{\"Value\":\"true\"}}}}}]},\"isHiddenInViewMode\":false}]",
          "height": 380.47,
          "width": 429.49,
          "x": 1151.91,
          "y": 510.01,
          "z": 3000.00
        },
        {
          "config": "{\"name\":\"da2718739b12f7cf91e7\",\"layouts\":[{\"id\":0,\"position\":{\"x\":347.7905236907731,\"y\":43.18204488778055,\"z\":7000,\"width\":1252.279301745636,\"height\":380.4688279301746,\"tabOrder\":8000}}],\"singleVisual\":{\"visualType\":\"shape\",\"drillFilterOtherVisuals\":true,\"objects\":{\"shape\":[{\"properties\":{\"tileShape\":{\"expr\":{\"Literal\":{\"Value\":\"'rectangle'\"}}},\"roundEdge\":{\"expr\":{\"Literal\":{\"Value\":\"10L\"}}}}}],\"rotation\":[{\"properties\":{\"shapeAngle\":{\"expr\":{\"Literal\":{\"Value\":\"0L\"}}}}}],\"fill\":[{\"properties\":{\"fillColor\":{\"solid\":{\"color\":{\"expr\":{\"ThemeDataColor\":{\"ColorId\":0,\"Percent\":0}}}}}},\"selector\":{\"id\":\"default\"}},{\"properties\":{\"show\":{\"expr\":{\"Literal\":{\"Value\":\"true\"}}}}}],\"outline\":[{\"properties\":{\"show\":{\"expr\":{\"Literal\":{\"Value\":\"false\"}}}}}],\"shadow\":[{\"properties\":{\"show\":{\"expr\":{\"Literal\":{\"Value\":\"true\"}}}}},{\"properties\":{\"color\":{\"solid\":{\"color\":{\"expr\":{\"ThemeDataColor\":{\"ColorId\":0,\"Percent\":-0.6}}}}},\"shadowPositionPreset\":{\"expr\":{\"Literal\":{\"Value\":\"'custom'\"}}},\"transparency\":{\"expr\":{\"Literal\":{\"Value\":\"90D\"}}}},\"selector\":{\"id\":\"default\"}}]}},\"howCreated\":\"InsertVisualButton\"}",
          "filters": "[]",
          "height": 380.47,
          "width": 1252.28,
          "x": 347.79,
          "y": 43.18,
          "z": 7000.00
        },
        {
          "config": "{\"name\":\"deaefd744b8d5df4c9fd\",\"layouts\":[{\"id\":0,\"position\":{\"x\":598.713216957606,\"y\":490,\"z\":4000,\"width\":468,\"height\":420.14962593516213,\"tabOrder\":4000}}],\"singleVisual\":{\"visualType\":\"shape\",\"drillFilterOtherVisuals\":true,\"objects\":{\"shape\":[{\"properties\":{\"tileShape\":{\"expr\":{\"Literal\":{\"Value\":\"'rectangle'\"}}},\"roundEdge\":{\"expr\":{\"Literal\":{\"Value\":\"10L\"}}}}}],\"rotation\":[{\"properties\":{\"shapeAngle\":{\"expr\":{\"Literal\":{\"Value\":\"0L\"}}}}}],\"fill\":[{\"properties\":{\"fillColor\":{\"solid\":{\"color\":{\"expr\":{\"ThemeDataColor\":{\"ColorId\":0,\"Percent\":0}}}}}},\"selector\":{\"id\":\"default\"}}],\"outline\":[{\"properties\":{\"show\":{\"expr\":{\"Literal\":{\"Value\":\"false\"}}}}}],\"shadow\":[{\"properties\":{\"show\":{\"expr\":{\"Literal\":{\"Value\":\"true\"}}}}},{\"properties\":{\"shadowPositionPreset\":{\"expr\":{\"Literal\":{\"Value\":\"'custom'\"}}},\"transparency\":{\"expr\":{\"Literal\":{\"Value\":\"90D\"}}},\"color\":{\"solid\":{\"color\":{\"expr\":{\"ThemeDataColor\":{\"ColorId\":0,\"Percent\":-0.6}}}}}},\"selector\":{\"id\":\"default\"}}]}},\"howCreated\":\"InsertVisualButton\"}",
          "filters": "[]",
          "height": 420.15,
          "width": 468.00,
          "x": 598.71,
          "y": 490.00,
          "z": 4000.00
        },
        {
          "config": "{\"name\":\"f033554af8ad0fe7d3fe\",\"layouts\":[{\"id\":0,\"position\":{\"x\":60.68827930174564,\"y\":490,\"z\":0,\"width\":468,\"height\":420.14962593516213,\"tabOrder\":3000}}],\"singleVisual\":{\"visualType\":\"shape\",\"drillFilterOtherVisuals\":true,\"objects\":{\"shape\":[{\"properties\":{\"tileShape\":{\"expr\":{\"Literal\":{\"Value\":\"'rectangle'\"}}},\"roundEdge\":{\"expr\":{\"Literal\":{\"Value\":\"10L\"}}}}}],\"rotation\":[{\"properties\":{\"shapeAngle\":{\"expr\":{\"Literal\":{\"Value\":\"0L\"}}}}}],\"fill\":[{\"properties\":{\"fillColor\":{\"solid\":{\"color\":{\"expr\":{\"ThemeDataColor\":{\"ColorId\":0,\"Percent\":0}}}}}},\"selector\":{\"id\":\"default\"}},{\"properties\":{\"show\":{\"expr\":{\"Literal\":{\"Value\":\"true\"}}}}}],\"outline\":[{\"properties\":{\"show\":{\"expr\":{\"Literal\":{\"Value\":\"false\"}}}}}],\"shadow\":[{\"properties\":{\"show\":{\"expr\":{\"Literal\":{\"Value\":\"true\"}}}}},{\"properties\":{\"color\":{\"solid\":{\"color\":{\"expr\":{\"ThemeDataColor\":{\"ColorId\":0,\"Percent\":-0.6}}}}},\"shadowPositionPreset\":{\"expr\":{\"Literal\":{\"Value\":\"'custom'\"}}},\"transparency\":{\"expr\":{\"Literal\":{\"Value\":\"90D\"}}}},\"selector\":{\"id\":\"default\"}}]}},\"howCreated\":\"InsertVisualButton\"}",
          "filters": "[]",
          "height": 420.15,
          "width": 468.00,
          "x": 60.69,
          "y": 490.00,
          "z": 0.00
        }
      ],
      "width": 1664.00
    }
  ]
}